java/__init__.py
java/awt/__init__.py
java/awt/event/__init__.py
java/awt/geom/__init__.py
java/awt/image/__init__.py
java/awt/print/__init__.py
java/beans/__init__.py
java/io/__init__.py
java/lang/__init__.py
java/lang/reflect/__init__.py
java/math/__init__.py
java/net/__init__.py
java/net/http/__init__.py
java/nio/__init__.py
java/nio/channels/__init__.py
java/nio/charset/__init__.py
java/nio/file/__init__.py
java/nio/file/attribute/__init__.py
java/org/__init__.py
java/org/jdesktop/__init__.py
java/org/jdesktop/core/__init__.py
java/org/jdesktop/core/animation/__init__.py
java/org/jdesktop/core/animation/timing/__init__.py
java/security/__init__.py
java/text/__init__.py
java/time/__init__.py
java/time/chrono/__init__.py
java/time/format/__init__.py
java/time/temporal/__init__.py
java/util/__init__.py
java/util/concurrent/__init__.py
java/util/function/__init__.py
java/util/regex/__init__.py
java/util/stream/__init__.py
javax/__init__.py
javax/security/__init__.py
javax/security/auth/__init__.py
javax/swing/__init__.py
javax/swing/event/__init__.py
javax/swing/plaf/__init__.py
javax/swing/text/__init__.py
java_api-17.26.0.dist-info/LICENSE
java_api-17.26.0.dist-info/METADATA
java_api-17.26.0.dist-info/WHEEL
java_api-17.26.0.dist-info/top_level.txt
java_api-17.26.0.dist-info/RECORD
