Metadata-Version: 2.1
Name: java-api
Version: 17.26.0
Summary: Java API Specification for ignition-api
Home-page: https://github.com/ignition-devs/java-api
Author: César Román
Author-email: cesar@coatl.dev
License: MIT
Project-URL: Source, https://github.com/ignition-devs/java-api/tree/main
Project-URL: Documentation, https://docs.oracle.com/en/java/javase/17/docs/api/index.html
Project-URL: Funding, https://github.com/sponsors/cesarcoatl
Project-URL: Tracker, https://github.com/ignition-devs/java-api/issues
Keywords: coatl.dev,ignition,inductive automation,java
Platform: UNKNOWN
Classifier: Development Status :: 5 - Production/Stable
Classifier: Intended Audience :: Developers
Classifier: Intended Audience :: Information Technology
Classifier: Intended Audience :: Manufacturing
Classifier: Operating System :: MacOS :: MacOS X
Classifier: Operating System :: Microsoft :: Windows
Classifier: Operating System :: POSIX :: Linux
Classifier: Programming Language :: Python
Classifier: Programming Language :: Python :: 2
Classifier: Programming Language :: Python :: 2 :: Only
Classifier: Programming Language :: Python :: 2.7
Classifier: Topic :: Software Development :: Libraries :: Python Modules
Classifier: Topic :: Software Development :: Testing :: Mocking
Requires-Python: ==2.7.18
Requires-Dist: typing
